Src/pc/pc.sv
module pc (
    input logic clk,
    input logic rst,
    input logic branch_en,
    input logic [22:0] branch_offset,
    input logic nzp_en,
    input logic [2:0] nzp_flag,
    input logic [2:0] nzp_mask,
    output logic [31:0] pc_out
);

logic [2:0] nzp_reg;

initial begin
    $dumpfile("pc.vcd");
    $dumpvars(0, pc);
end


always_ff @( posedge clk or posedge rst ) begin 
    if (rst) begin
        pc_out <= 32'b0;
        nzp_reg <= 3'b000;
    end else if (nzp_en) begin
        nzp_reg <= nzp_flag;
    end else if (branch_en) begin
        if ((nzp_reg & nzp_mask) != 0) begin
            pc_out <= pc_out + branch_offset;
        end else begin
            pc_out <= pc_out + 1; 
        end
    end else begin
        pc_out <= pc_out + 1; 
    end
end
    
endmodule

Src/pc/pc.vcd
$date
	Wed Apr 29 17:51:35 2026
$end
$version
	Icarus Verilog
$end
$timescale
	1ps
$end
$scope module pc $end
$var wire 1 ! branch_en $end
$var wire 23 " branch_offset [22:0] $end
$var wire 1 # clk $end
$var wire 1 $ nzp_en $end
$var wire 3 % nzp_flag [2:0] $end
$var wire 3 & nzp_mask [2:0] $end
$var wire 1 ' rst $end
$var reg 3 ( nzp_reg [2:0] $end
$var reg 32 ) pc_out [31:0] $end
$upscope $end
$enddefinitions $end
$comment Show the parameter values. $end
$dumpall
$end
#0
$dumpvars
b0 )
b0 (
1'
b0 &
b0 %
0$
1#
b0 "
0!
$end
#5000
0#
#10000
1#
#15001
0#
#20001
0'
1#
#25001
0#
#30001
b1 )
1#
#35001
0#
#40001
b10 )
1#
#45001
0#
#50001
b11 )
1#
#51002
b0 )
1'
#56002
0#
#61002
0'
1#
#66002
0#
#71002
b1 %
1$
b1 )
1#
#76002
0#
#81002
b101 "
b1 &
1!
0$
b1 (
1#
#86002
0#
#91002
b110 )
1#
#92003
b0 (
b0 )
1'
b0 &
b0 %
b0 "
0!
#97003
0#
#102003
0'
1#
#107003
0#
#112003
b1 %
1$
b1 )
1#
#117003
0#
#122003
b101 "
b1 &
1!
0$
b1 (
1#
#127003
0#
#132003
b110 )
1#
#133004
b0 (
b0 )
1'
b0 &
b0 %
b0 "
0!
#138004
0#
#143004
0'
1#
#148004
0#
#153004
b1 %
1$
b1 )
1#
#158004
0#
#163004
b101 "
b100 &
1!
0$
b1 (
1#
#168004
0#
#173004
b10 )
1#
